{
   "files": [   
 {
         "name":"TH_TRUE-01",
         "url": "https://raw.githubusercontent.com/Vpnball/test99/main/TH_TRUE-01.ovpn"
 },

      "name":"TH_DTAC-01",
         "url":"https://raw.githubusercontent.com/Vpnball/test99/main/TH_DTAC-01.ovpn"
      },    
    
       "name":"TRUE",
         "url":"https://raw.githubusercontent.com/Vpnball/test99/main/TRUE.ovpn"
      },
      
     { 
      "name":"DTAC",
         "url":"https://raw.githubusercontent.com/Vpnball/test99/main/DTAC.ovpn"
     }



      
],
   
"message":" \nรองรับ TRUE-DTAC\nบอลหลังหลัง\n  ",
   "title":"ไฟล์อัพเดทใหม่พร้อมใช้งาน" ,
   "version": 2.4
}
